spectryn/__init__.py
spectryn/py.typed
spectryn/testing.py
spectryn/adapters/__init__.py
spectryn/adapters/asana/__init__.py
spectryn/adapters/asana/adapter.py
spectryn/adapters/asana/async_adapter.py
spectryn/adapters/asana/batch.py
spectryn/adapters/asana/cached_adapter.py
spectryn/adapters/async_base/__init__.py
spectryn/adapters/async_base/bounded_concurrency.py
spectryn/adapters/async_base/http_client.py
spectryn/adapters/async_base/http_client_sync.py
spectryn/adapters/async_base/parallel.py
spectryn/adapters/async_base/rate_limiter.py
spectryn/adapters/async_base/retry_utils.py
spectryn/adapters/async_base/token_bucket.py
spectryn/adapters/azure_devops/__init__.py
spectryn/adapters/azure_devops/adapter.py
spectryn/adapters/azure_devops/async_adapter.py
spectryn/adapters/azure_devops/batch.py
spectryn/adapters/azure_devops/client.py
spectryn/adapters/azure_devops/plugin.py
spectryn/adapters/basecamp/__init__.py
spectryn/adapters/basecamp/adapter.py
spectryn/adapters/basecamp/client.py
spectryn/adapters/bitbucket/__init__.py
spectryn/adapters/bitbucket/adapter.py
spectryn/adapters/bitbucket/client.py
spectryn/adapters/bitbucket/server_client.py
spectryn/adapters/cache/__init__.py
spectryn/adapters/cache/backend.py
spectryn/adapters/cache/file_cache.py
spectryn/adapters/cache/keys.py
spectryn/adapters/cache/manager.py
spectryn/adapters/cache/memory.py
spectryn/adapters/cache/metadata.py
spectryn/adapters/cache/redis_cache.py
spectryn/adapters/clickup/__init__.py
spectryn/adapters/clickup/adapter.py
spectryn/adapters/clickup/client.py
spectryn/adapters/config/__init__.py
spectryn/adapters/config/environment.py
spectryn/adapters/config/file_config.py
spectryn/adapters/confluence/__init__.py
spectryn/adapters/confluence/adapter.py
spectryn/adapters/confluence/client.py
spectryn/adapters/confluence/plugin.py
spectryn/adapters/event_store/__init__.py
spectryn/adapters/event_store/file_store.py
spectryn/adapters/event_store/memory_store.py
spectryn-1.0.0.dist-info/licenses/LICENSE
spectryn-1.0.0.dist-info/METADATA
spectryn-1.0.0.dist-info/WHEEL
spectryn-1.0.0.dist-info/entry_points.txt
spectryn-1.0.0.dist-info/top_level.txt
spectryn-1.0.0.dist-info/RECORD
