Metadata-Version: 2.4
Name: spectryn
Version: 1.0.0
Summary: A production-grade CLI tool for synchronizing markdown specifications with issue trackers
Author-email: Adrian Darian <adrian.the.hactus@gmail.com>
License: MIT
Project-URL: Homepage, https://github.com/adriandarian/spectryn
Project-URL: Documentation, https://github.com/adriandarian/spectryn#readme
Project-URL: Repository, https://github.com/adriandarian/spectryn.git
Project-URL: Issues, https://github.com/adriandarian/spectryn/issues
Project-URL: Changelog, https://github.com/adriandarian/spectryn/blob/main/CHANGELOG.md
Keywords: jira,github,azure-devops,linear,markdown,sync,issue-tracker,agile,project-management,cli
Classifier: Development Status :: 4 - Beta
Classifier: Environment :: Console
Classifier: Intended Audience :: Developers
Classifier: License :: OSI Approved :: MIT License
Classifier: Operating System :: OS Independent
Classifier: Programming Language :: Python :: 3
Classifier: Programming Language :: Python :: 3.11
Classifier: Programming Language :: Python :: 3.12
Classifier: Programming Language :: Python :: 3.13
Classifier: Programming Language :: Python :: 3.14
Classifier: Topic :: Software Development :: Documentation
Classifier: Topic :: Software Development :: Bug Tracking
Classifier: Typing :: Typed
Requires-Python: >=3.11
License-File: LICENSE
Requires-Dist: requests>=2.28.0
Requires-Dist: pyyaml>=6.0
Requires-Dist: tomli>=2.0; python_version < "3.11"
Provides-Extra: async
Requires-Dist: aiohttp>=3.8.0; extra == "async"
Provides-Extra: redis
Requires-Dist: redis>=4.5.0; extra == "redis"
Provides-Extra: gitlab
Requires-Dist: python-gitlab>=4.0.0; extra == "gitlab"
Provides-Extra: bitbucket
Requires-Dist: atlassian-python-api>=3.0.0; extra == "bitbucket"
Provides-Extra: telemetry
Requires-Dist: opentelemetry-api>=1.20.0; extra == "telemetry"
Requires-Dist: opentelemetry-sdk>=1.20.0; extra == "telemetry"
Requires-Dist: opentelemetry-exporter-otlp>=1.20.0; extra == "telemetry"
Requires-Dist: opentelemetry-exporter-prometheus>=0.41b0; extra == "telemetry"
Provides-Extra: prometheus
Requires-Dist: prometheus_client>=0.17.0; extra == "prometheus"
Provides-Extra: dev
Requires-Dist: pytest>=7.0; extra == "dev"
Requires-Dist: pytest-cov>=4.0; extra == "dev"
Requires-Dist: pytest-mock>=3.10; extra == "dev"
Requires-Dist: pytest-asyncio>=0.21.0; extra == "dev"
Requires-Dist: pytest-xdist>=3.5.0; extra == "dev"
Requires-Dist: pytest-timeout>=2.3.0; extra == "dev"
Requires-Dist: pytest-benchmark>=4.0; extra == "dev"
Requires-Dist: hypothesis>=6.0; extra == "dev"
Requires-Dist: mutmut>=2.4; extra == "dev"
Requires-Dist: aiohttp>=3.8.0; extra == "dev"
Requires-Dist: mypy>=1.0; extra == "dev"
Requires-Dist: ruff>=0.1.0; extra == "dev"
Requires-Dist: pre-commit>=3.0; extra == "dev"
Requires-Dist: types-PyYAML>=6.0; extra == "dev"
Requires-Dist: redis>=4.5.0; extra == "dev"
Requires-Dist: types-redis>=4.5.0; extra == "dev"
Provides-Extra: all
Requires-Dist: aiohttp>=3.8.0; extra == "all"
Requires-Dist: redis>=4.5.0; extra == "all"
Requires-Dist: python-gitlab>=4.0.0; extra == "all"
Requires-Dist: atlassian-python-api>=3.0.0; extra == "all"
Requires-Dist: opentelemetry-api>=1.20.0; extra == "all"
Requires-Dist: opentelemetry-sdk>=1.20.0; extra == "all"
Requires-Dist: opentelemetry-exporter-otlp>=1.20.0; extra == "all"
Requires-Dist: opentelemetry-exporter-prometheus>=0.41b0; extra == "all"
Requires-Dist: prometheus_client>=0.17.0; extra == "all"
Provides-Extra: docs
Requires-Dist: mkdocs>=1.5; extra == "docs"
Requires-Dist: mkdocs-material>=9.0; extra == "docs"
Provides-Extra: tui
Requires-Dist: textual>=0.85.0; extra == "tui"
Dynamic: license-file
